camagick/__init__.py
camagick/_version.py
camagick/application.py
camagick/caguard.py
camagick/camagick_BACKUP_87205.py
camagick/camagick_BASE_87205.py
camagick/camagick_LOCAL_87205.py
camagick/camagick_REMOTE_87205.py
camagick/caspy.py
camagick/epics.py
camagick/executor.py
camagick/helpers.py
camagick/ioc.py
camagick/monitor.py
camagick/probe.py
camagick/processor.py
camagick/reader.py
camagick/stash.py
camagick/subapp.py
camagick/display/application.py
camagick/display/image.py
camagick/flow/chain.py
camagick/flow/fanout.py
camagick/pipe/__init__.py
camagick/pipe/demote.py
camagick/pipe/eval.py
camagick/pipe/exclude.py
camagick/pipe/idem.py
camagick/pipe/max.py
camagick/pipe/min.py
camagick/pipe/nonempty.py
camagick/pipe/npfun.py
camagick/pipe/only.py
camagick/pipe/pace.py
camagick/pipe/promote.py
camagick/pipe/rename.py
camagick/pipe/reshape.py
camagick/pipe/slice.py
camagick/pipe/stack.py
camagick/pipe/sum.py
camagick/sink/__init__.py
camagick/sink/astor.py
camagick/sink/epics.py
camagick/sink/hdf5.py
camagick/sink/ioc.py
camagick/sink/plot.py
camagick/sink/summary.py
camagick/sink/tango.py
camagick/sink/tiff.py
camagick/sink/zarr.py
camagick/source/__init__.py
camagick/source/astor.py
camagick/source/epics.py
camagick/source/eval.py
camagick/source/hdf5.py
camagick/source/ioc.py
camagick/source/ophyd.py
camagick/source/scratch.py
camagick/source/tango.py
camagick/source/zarr.py
camagick/storage/base.py
camagick/storage/hdf5.py
camagick/storage/memory.py
camagick-0.4.0.dist-info/licenses/COPYING.md
camagick-0.4.0.dist-info/METADATA
camagick-0.4.0.dist-info/WHEEL
camagick-0.4.0.dist-info/entry_points.txt
camagick-0.4.0.dist-info/top_level.txt
camagick-0.4.0.dist-info/RECORD
