Metadata-Version: 2.4
Name: camagick
Version: 0.4.0
Summary: Command-line client tools for EPICS-CA data processing
Author-email: Florin Boariu <florin.pt@rootshell.ro>, Matthias Rössle <matthias.roessle@helmholtz-berlin.de>
License-Expression: GPL-3.0-or-later
Project-URL: Source Code, https://gitlab.com/kmc3-xpp/camagick
Project-URL: Bug Tracker, https://gitlab.com/kmc3-xpp/camagick/-/issues
Classifier: Programming Language :: Python :: 3
Classifier: Operating System :: POSIX :: Linux
Classifier: Development Status :: 2 - Pre-Alpha
Classifier: Environment :: Console
Classifier: Intended Audience :: Science/Research
Classifier: Topic :: Scientific/Engineering
Requires-Python: >=3.8
License-File: COPYING.md
Requires-Dist: schema
Requires-Dist: numpy
Requires-Dist: asteval
Provides-Extra: all
Requires-Dist: camagick[epics,hdf5,legacy,plot,tango,test,tiff,zarr]; extra == "all"
Provides-Extra: epics
Requires-Dist: xarray; extra == "epics"
Requires-Dist: caproto; extra == "epics"
Requires-Dist: parse; extra == "epics"
Provides-Extra: tango
Requires-Dist: pytango>=10.0; extra == "tango"
Provides-Extra: legacy
Requires-Dist: ophyd; extra == "legacy"
Provides-Extra: tiff
Requires-Dist: tifffile; extra == "tiff"
Provides-Extra: zarr
Requires-Dist: zarr; extra == "zarr"
Provides-Extra: plot
Requires-Dist: matplotlib; extra == "plot"
Provides-Extra: hdf5
Requires-Dist: h5py; extra == "hdf5"
Provides-Extra: test
Requires-Dist: pytest; extra == "test"
Requires-Dist: pytest-cov; extra == "test"
Requires-Dist: pytest-asyncio; extra == "test"
Dynamic: license-file
